dmae/__init__.py
dmae/dissimilarities.py
dmae/initializers.py
dmae/layers.py
dmae/losses.py
dmae/metrics.py
dmae/normalizers.py
dmae_gpu-1.1.2.dist-info/LICENSE
dmae_gpu-1.1.2.dist-info/METADATA
dmae_gpu-1.1.2.dist-info/WHEEL
dmae_gpu-1.1.2.dist-info/top_level.txt
dmae_gpu-1.1.2.dist-info/RECORD
